BEAT/__init__.py
BEAT/_cate_estimator.py
BEAT/_ortho_learner.py
BEAT/_shap.py
BEAT/_tree_exporter.py
BEAT/_version.py
BEAT/bootstrap.py
BEAT/causal_forest.py
BEAT/deepiv.py
BEAT/dowhy.py
BEAT/drlearner.py
BEAT/ortho_forest.py
BEAT/ortho_iv.py
BEAT/two_stage_least_squares.py
BEAT/utilities.py
GuangBEAT-1.0.dist-info/LICENSE
GuangBEAT-1.0.dist-info/METADATA
GuangBEAT-1.0.dist-info/WHEEL
GuangBEAT-1.0.dist-info/top_level.txt
GuangBEAT-1.0.dist-info/RECORD
