Metadata-Version: 2.1
Name: GuangBEAT
Version: 1.0
Summary: BEAT
Author: luzgool
License: MIT
Keywords: treatment-effect
Classifier: Programming Language :: Python :: 3.6
Classifier: Programming Language :: Python :: 3.7
Classifier: Programming Language :: Python :: 3.8
Classifier: Programming Language :: Python :: 3.9
Classifier: License :: OSI Approved :: MIT License
Classifier: Operating System :: MacOS
Classifier: Operating System :: Microsoft :: Windows
Classifier: Operating System :: POSIX :: Linux
License-File: LICENSE
Requires-Dist: numpy
Requires-Dist: scipy (>1.4.0)
Requires-Dist: scikit-learn (<1.2,>0.22.0)
Requires-Dist: sparse
Requires-Dist: joblib (>=0.13.0)
Requires-Dist: statsmodels (>=0.10)
Requires-Dist: pandas
Requires-Dist: shap (<0.41.0,>=0.38.1)
Requires-Dist: dowhy (<0.8)
Requires-Dist: lightgbm
Provides-Extra: all
Requires-Dist: azure-cli ; extra == 'all'
Requires-Dist: keras (<2.4) ; extra == 'all'
Requires-Dist: tensorflow (<2.3,>1.10) ; extra == 'all'
Requires-Dist: protobuf (<4) ; extra == 'all'
Requires-Dist: matplotlib ; extra == 'all'
Provides-Extra: automl
Requires-Dist: azure-cli ; extra == 'automl'
Provides-Extra: plt
Requires-Dist: graphviz ; extra == 'plt'
Requires-Dist: matplotlib ; extra == 'plt'
Provides-Extra: tf
Requires-Dist: protobuf (<4) ; extra == 'tf'
Requires-Dist: keras (<2.4) ; (python_version < "3.9") and extra == 'tf'
Requires-Dist: tensorflow (<2.3,>1.10) ; (python_version < "3.9") and extra == 'tf'
